[
    { "ref":"20.1", "vers":"O vinho produz zombadores; o álcool leva a brigas; quem é dominado pela bebida não é sábio." },
    { "ref":"21.17", "vers":"Quem ama os prazeres ficará pobre; quem ama o vinho e o luxo nunca enriquecerá." },
    { "ref":"23.31", "vers":"Não olhe demoradamente para o vinho, observando quanto ele é vermelho; como brilha no copo e desce suavemente." },
    { "ref":"1.9", "vers":"VERSICULO ASDASDASDASDASDASDASDA" },
    { "ref":"1.9", "vers":"VERSICULO ASDASDASDASDASDASDASDA" }
]